platformeb/__init__.py
platformeb/driver.py
platformeb/pages/__init__.py
platformeb/pages/abstract_page.py
platformeb/pages/web_page.py
platformeb/types.py
platformeb/utils/__init__.py
platformeb/utils/logger.py
platformeb-0.1.7.dist-info/METADATA
platformeb-0.1.7.dist-info/WHEEL
platformeb-0.1.7.dist-info/RECORD
