Metadata-Version: 2.3
Name: platformeb
Version: 0.1.7
Summary: 
Author: Yan
Author-email: 119687802+sndmndss@users.noreply.github.com
Requires-Python: >=3.13,<4.0
Classifier: Development Status :: 4 - Beta
Classifier: Intended Audience :: Developers
Classifier: Topic :: Software Development :: Libraries :: Python Modules
Classifier: Programming Language :: Python :: 3
Classifier: Programming Language :: Python :: 3.8
Classifier: Programming Language :: Python :: 3.9
Classifier: Programming Language :: Python :: 3.10
Classifier: Programming Language :: Python :: 3.11
Classifier: Programming Language :: Python :: 3.12
Classifier: Operating System :: OS Independent
Requires-Dist: appium-python-client (>=5.0.0,<6.0.0)
Requires-Dist: loguru (>=0.7.3,<0.8.0)
Requires-Dist: selenium (>=4.31.0,<5.0.0)
Requires-Dist: webdriver-manager (>=4.0.2,<5.0.0)
